LICENSE
MANIFEST.in
README.md
requirements.txt
setup.cfg
setup.py
tmuxp_combine/__init__.py
tmuxp_combine/__main__.py
tmuxp_combine/core.py
tmuxp_combine/exceptions.py
tmuxp_combine/main.py
tmuxp_combine/parser_utils.py
tmuxp_combine.egg-info/PKG-INFO
tmuxp_combine.egg-info/SOURCES.txt
tmuxp_combine.egg-info/dependency_links.txt
tmuxp_combine.egg-info/entry_points.txt
tmuxp_combine.egg-info/requires.txt
tmuxp_combine.egg-info/top_level.txt
tmuxp_combine/commands/__init__.py
tmuxp_combine/commands/load.py
tmuxp_combine/commands/session/__init__.py
tmuxp_combine/commands/session/list.py
tmuxp_combine/commands/session/load.py
tmuxp_combine/commands/session/show.py
tmuxp_combine/commands/window/__init__.py
tmuxp_combine/commands/window/list.py