Metadata-Version: 1.1
Name: tmuxp-combine
Version: 0.0.2
Summary: A tool for combining tmuxp configs
Home-page: https://github.com/szopu/tmuxp-combine
Author: Andrzej Pragacz
Author-email: apragacz@o2.pl
License: MIT
Keywords: tmux tmuxp cli
Platform: UNKNOWN
Classifier: Development Status :: 2 - Pre-Alpha
Classifier: Environment :: Console
Classifier: Intended Audience :: Developers
Classifier: License :: OSI Approved :: MIT License
Classifier: Operating System :: POSIX
Classifier: Operating System :: POSIX :: Linux
Classifier: Programming Language :: Python
Classifier: Programming Language :: Python :: 2.7
Classifier: Programming Language :: Python :: 3
Classifier: Topic :: Utilities
